boilee/__init__.py
boilee/__main__.py
boilee/database.py
boilee/utils.py
boilee/scripts/__init__.py
boilee/scripts/boilee.py
boilee/scripts/make.py
boilee/scripts/run.py
boilee-1.0.0.dist-info/LICENSE
boilee-1.0.0.dist-info/METADATA
boilee-1.0.0.dist-info/WHEEL
boilee-1.0.0.dist-info/entry_points.txt
boilee-1.0.0.dist-info/top_level.txt
boilee-1.0.0.dist-info/RECORD
