Metadata-Version: 2.1
Name: boilee
Version: 1.0.0
Summary: An easy way to create a tool to generate code boilerplates like "npm init" and "vue create" for any programming language.
Home-page: https://github.com/vadolasi/boilee
Author: Vitor Daniel
Author-email: vitor036daniel@gmail.com
License: UNKNOWN
Project-URL: Bug Reports, https://github.com/vadolasi/boilee/issues
Project-URL: Funding, https://donate.pypi.org
Project-URL: Say Thanks!, https://saythanks.io/to/vitor036daniel@gmail.com
Project-URL: Source, https://github.com/vadolasi/boilee/
Keywords: boilerplate cli generator templating
Platform: UNKNOWN
Classifier: Development Status :: 3 - Alpha
Classifier: Intended Audience :: Developers
Classifier: Topic :: Software Development :: Code Generators
Classifier: License :: OSI Approved :: GNU General Public License (GPL)
Classifier: Operating System :: OS Independent
Classifier: Programming Language :: Python :: 3.8
Requires-Python: >=3.8, <3.9
Requires-Dist: click (==7.1.2)
Requires-Dist: commonmark (==0.9.1)
Requires-Dist: docopt (==0.6.2)
Requires-Dist: gitignore-parser (==0.0.8)
Requires-Dist: halo (==0.0.30)
Requires-Dist: jinja2 (==2.11.2)
Requires-Dist: log-symbols (==0.0.14)
Requires-Dist: prompt-toolkit (==1.0.14)
Requires-Dist: pyfiglet (==0.8.post1)
Requires-Dist: pyinquirer (==1.0.3)
Requires-Dist: pyyaml (==5.3.1)
Requires-Dist: regex (==2020.10.28)
Requires-Dist: rich (==9.1.0)
Requires-Dist: spinners (==0.0.24)
Requires-Dist: sqlalchemy (==1.3.20)
Requires-Dist: termcolor (==1.1.0)
Requires-Dist: typing-extensions (==3.7.4.3)
Requires-Dist: unipath (==1.1)
Requires-Dist: wcwidth (==0.2.5)
Requires-Dist: six (==1.15.0) ; python_version >= "2.7" and python_version not in "3.0, 3.1, 3.2"
Requires-Dist: markupsafe (==1.1.1) ; python_version >= "2.7" and python_version not in "3.0, 3.1, 3.2, 3.3"
Requires-Dist: colorama (==0.4.4) ; python_version >= "2.7" and python_version not in "3.0, 3.1, 3.2, 3.3, 3.4"
Requires-Dist: pygments (==2.7.2) ; python_version >= "3.5"
Provides-Extra: dev
Requires-Dist: appdirs (==1.4.4) ; extra == 'dev'
Requires-Dist: black (==20.8b1) ; extra == 'dev'
Requires-Dist: certifi (==2020.6.20) ; extra == 'dev'
Requires-Dist: cffi (==1.14.3) ; extra == 'dev'
Requires-Dist: chardet (==3.0.4) ; extra == 'dev'
Requires-Dist: click (==7.1.2) ; extra == 'dev'
Requires-Dist: isort (==5.6.4) ; extra == 'dev'
Requires-Dist: mypy-extensions (==0.4.3) ; extra == 'dev'
Requires-Dist: pathspec (==0.8.0) ; extra == 'dev'
Requires-Dist: pkginfo (==1.6.1) ; extra == 'dev'
Requires-Dist: readme-renderer (==28.0) ; extra == 'dev'
Requires-Dist: regex (==2020.10.28) ; extra == 'dev'
Requires-Dist: requests-toolbelt (==0.9.1) ; extra == 'dev'
Requires-Dist: rfc3986 (==1.4.0) ; extra == 'dev'
Requires-Dist: toml (==0.10.1) ; extra == 'dev'
Requires-Dist: twine (==3.2.0) ; extra == 'dev'
Requires-Dist: typed-ast (==1.4.1) ; extra == 'dev'
Requires-Dist: typing-extensions (==3.7.4.3) ; extra == 'dev'
Requires-Dist: webencodings (==0.5.1) ; extra == 'dev'
Requires-Dist: tqdm (==4.51.0) ; (python_version >= "2.6" and python_version not in "3.0, 3.1") and extra == 'dev'
Requires-Dist: pyparsing (==2.4.7) ; (python_version >= "2.6" and python_version not in "3.0, 3.1, 3.2") and extra == 'dev'
Requires-Dist: six (==1.15.0) ; (python_version >= "2.7" and python_version not in "3.0, 3.1, 3.2") and extra == 'dev'
Requires-Dist: idna (==2.10) ; (python_version >= "2.7" and python_version not in "3.0, 3.1, 3.2, 3.3") and extra == 'dev'
Requires-Dist: packaging (==20.4) ; (python_version >= "2.7" and python_version not in "3.0, 3.1, 3.2, 3.3") and extra == 'dev'
Requires-Dist: pycparser (==2.20) ; (python_version >= "2.7" and python_version not in "3.0, 3.1, 3.2, 3.3") and extra == 'dev'
Requires-Dist: bleach (==3.2.1) ; (python_version >= "2.7" and python_version not in "3.0, 3.1, 3.2, 3.3, 3.4") and extra == 'dev'
Requires-Dist: colorama (==0.4.4) ; (python_version >= "2.7" and python_version not in "3.0, 3.1, 3.2, 3.3, 3.4") and extra == 'dev'
Requires-Dist: cryptography (==3.2.1) ; (python_version >= "2.7" and python_version not in "3.0, 3.1, 3.2, 3.3, 3.4") and extra == 'dev'
Requires-Dist: docutils (==0.16) ; (python_version >= "2.7" and python_version not in "3.0, 3.1, 3.2, 3.3, 3.4") and extra == 'dev'
Requires-Dist: requests (==2.24.0) ; (python_version >= "2.7" and python_version not in "3.0, 3.1, 3.2, 3.3, 3.4") and extra == 'dev'
Requires-Dist: urllib3 (==1.25.11) ; (python_version >= "2.7" and python_version not in "3.0, 3.1, 3.2, 3.3, 3.4" and python_version < "4") and extra == 'dev'
Requires-Dist: pygments (==2.7.2) ; (python_version >= "3.5") and extra == 'dev'
Requires-Dist: keyring (==21.4.0) ; (python_version >= "3.6") and extra == 'dev'
Requires-Dist: jeepney (==0.4.3) ; (sys_platform == "linux") and extra == 'dev'
Requires-Dist: secretstorage (==3.1.2) ; (sys_platform == "linux") and extra == 'dev'
